mediqbox/jobctxmgr/__init__.py
mediqbox/jobctxmgr/context.py
mediqbox/jobctxmgr/serialize.py
mediqbox/jobctxmgr/settings.py
mediqbox_jobctxmgr-0.0.2.dist-info/METADATA
mediqbox_jobctxmgr-0.0.2.dist-info/WHEEL
mediqbox_jobctxmgr-0.0.2.dist-info/top_level.txt
mediqbox_jobctxmgr-0.0.2.dist-info/RECORD
