Metadata-Version: 2.1
Name: mediqbox-jobctxmgr
Version: 0.0.2
Summary: A mediqbox component for job context management
Requires-Dist: influxdb3-python
